.gitignore
.mailmap
.readthedocs.yml
LICENSE.txt
README.rst
docker-compose.yml
setup.cfg
setup.py
tox.ini
.github/ISSUE_TEMPLATE.md
.github/workflows/codeqa_test.yaml
My_APScheduler.egg-info/PKG-INFO
My_APScheduler.egg-info/SOURCES.txt
My_APScheduler.egg-info/dependency_links.txt
My_APScheduler.egg-info/entry_points.txt
My_APScheduler.egg-info/not-zip-safe
My_APScheduler.egg-info/requires.txt
My_APScheduler.egg-info/top_level.txt
apscheduler/__init__.py
apscheduler/events.py
apscheduler/job.py
apscheduler/util.py
apscheduler/executors/__init__.py
apscheduler/executors/asyncio.py
apscheduler/executors/base.py
apscheduler/executors/base_py3.py
apscheduler/executors/debug.py
apscheduler/executors/gevent.py
apscheduler/executors/pool.py
apscheduler/executors/tornado.py
apscheduler/executors/twisted.py
apscheduler/jobstores/__init__.py
apscheduler/jobstores/base.py
apscheduler/jobstores/memory.py
apscheduler/jobstores/mongodb.py
apscheduler/jobstores/redis.py
apscheduler/jobstores/rethinkdb.py
apscheduler/jobstores/sqlalchemy.py
apscheduler/jobstores/zookeeper.py
apscheduler/schedulers/__init__.py
apscheduler/schedulers/asyncio.py
apscheduler/schedulers/background.py
apscheduler/schedulers/base.py
apscheduler/schedulers/blocking.py
apscheduler/schedulers/gevent.py
apscheduler/schedulers/qt.py
apscheduler/schedulers/tornado.py
apscheduler/schedulers/twisted.py
apscheduler/triggers/__init__.py
apscheduler/triggers/base.py
apscheduler/triggers/combining.py
apscheduler/triggers/date.py
apscheduler/triggers/interval.py
apscheduler/triggers/cron/__init__.py
apscheduler/triggers/cron/expressions.py
apscheduler/triggers/cron/fields.py
docs/conf.py
docs/contributing.rst
docs/extending.rst
docs/faq.rst
docs/index.rst
docs/migration.rst
docs/py-modindex.rst
docs/userguide.rst
docs/versionhistory.rst
docs/modules/events.rst
docs/modules/job.rst
docs/modules/schedulers.rst
docs/modules/executors/asyncio.rst
docs/modules/executors/base.rst
docs/modules/executors/debug.rst
docs/modules/executors/gevent.rst
docs/modules/executors/pool.rst
docs/modules/executors/twisted.rst
docs/modules/jobstores/base.rst
docs/modules/jobstores/memory.rst
docs/modules/jobstores/mongodb.rst
docs/modules/jobstores/redis.rst
docs/modules/jobstores/rethinkdb.rst
