Metadata-Version: 2.1
Name: My-APScheduler
Version: 3.9.3
Summary: In-process task scheduler with Cron-like capabilities
Home-page: https://github.com/agronholm/apscheduler
Author: Alex Grönholm
Author-email: apscheduler@nextday.fi
License: MIT
Keywords: scheduling cron
Platform: UNKNOWN
Classifier: Development Status :: 5 - Production/Stable
Classifier: Intended Audience :: Developers
Classifier: License :: OSI Approved :: MIT License
Classifier: Programming Language :: Python
Classifier: Programming Language :: Python :: 2.7
Classifier: Programming Language :: Python :: 3
Classifier: Programming Language :: Python :: 3.5
Classifier: Programming Language :: Python :: 3.6
Classifier: Programming Language :: Python :: 3.7
Classifier: Programming Language :: Python :: 3.8
Classifier: Programming Language :: Python :: 3.9
Classifier: Programming Language :: Python :: 3.10
Requires-Python: >=2.7, !=3.0.*, !=3.1.*, !=3.2.*, !=3.3.*, !=3.4.*, <4
Provides-Extra: asyncio
Provides-Extra: gevent
Provides-Extra: mongodb
Provides-Extra: redis
Provides-Extra: rethinkdb
Provides-Extra: sqlalchemy
Provides-Extra: tornado
Provides-Extra: twisted
Provides-Extra: zookeeper
Provides-Extra: testing
Provides-Extra: doc
License-File: LICENSE.txt
